logging_utils/__init__.py
logging_utils/logging_utils.py
logging_by_oriash-0.2.0.dist-info/LICENSE
logging_by_oriash-0.2.0.dist-info/METADATA
logging_by_oriash-0.2.0.dist-info/WHEEL
logging_by_oriash-0.2.0.dist-info/top_level.txt
logging_by_oriash-0.2.0.dist-info/RECORD
