Metadata-Version: 2.1
Name: logging-by-oriash
Version: 0.2.0
Summary: Custom Python logging library
Author: oriash93
License: MIT
Project-URL: Homepage, https://github.com/oriash93/logging-utils
Classifier: Programming Language :: Python
Classifier: Programming Language :: Python :: 3.10
Classifier: Programming Language :: Python :: 3.11
Classifier: Programming Language :: Python :: 3.12
Classifier: License :: OSI Approved :: MIT License
Classifier: Operating System :: OS Independent
Requires-Python: >=3.10
License-File: LICENSE
